edx_django_oauth2_provider-1.3.5.dist-info/METADATA
edx_django_oauth2_provider-1.3.5.dist-info/RECORD
edx_django_oauth2_provider-1.3.5.dist-info/WHEEL
edx_django_oauth2_provider-1.3.5.dist-info/top_level.txt
provider/__init__.py
provider/constants.py
provider/forms.py
provider/scope.py
provider/sphinx.py
provider/utils.py
provider/views.py
provider/management/__init__.py
provider/management/commands/__init__.py
provider/management/commands/_delete_common.py
provider/management/commands/delete_expired_access_tokens.py
provider/management/commands/delete_expired_grant_tokens.py
provider/oauth2/__init__.py
provider/oauth2/admin.py
provider/oauth2/backends.py
provider/oauth2/forms.py
provider/oauth2/managers.py
provider/oauth2/models.py
provider/oauth2/tests.py
provider/oauth2/urls.py
provider/oauth2/views.py
provider/oauth2/fixtures/test_oauth2.json
provider/oauth2/migrations/0001_initial.py
provider/oauth2/migrations/0002_auto_20160404_0813.py
provider/oauth2/migrations/0003_client_logout_uri.py
provider/oauth2/migrations/0004_add_index_on_grant_expires.py
provider/oauth2/migrations/0005_grant_nonce.py
provider/oauth2/migrations/__init__.py
provider/templates/provider/authorize.html
provider/templatetags/__init__.py
provider/templatetags/scope.py
provider/tests/__init__.py
provider/tests/test_mgmt_cmd.py
provider/tests/test_utils.py
