Metadata-Version: 1.1
Name: edx-django-oauth2-provider
Version: 1.3.5
Summary: edX fork of django-oauth2-provider
Home-page: https://github.com/edx/django-oauth2-provider
Author: edX
Author-email: oscm@edx.org
License: UNKNOWN
Platform: UNKNOWN
Classifier: Environment :: Web Environment
Classifier: Intended Audience :: Developers
Classifier: License :: OSI Approved :: MIT License
Classifier: Operating System :: OS Independent
Classifier: Programming Language :: Python
Classifier: Framework :: Django
Classifier: Programming Language :: Python :: 2
Classifier: Programming Language :: Python :: 2.7
Classifier: Programming Language :: Python :: 3
Classifier: Programming Language :: Python :: 3.5
Classifier: Programming Language :: Python :: 3.6
